lackey/App.py
lackey/Exceptions.py
lackey/Geometry.py
lackey/ImportHandler.py
lackey/InputEmulation.py
lackey/KeyCodes.py
lackey/PlatformManagerDarwin.py
lackey/PlatformManagerWindows.py
lackey/RegionMatching.py
lackey/SettingsDebug.py
lackey/SikuliGui.py
lackey/TemplateMatchers.py
lackey/__init__.py
lackey/_version.py
Lackey-0.7.3.dist-info/LICENSE.md
Lackey-0.7.3.dist-info/METADATA
Lackey-0.7.3.dist-info/WHEEL
Lackey-0.7.3.dist-info/top_level.txt
Lackey-0.7.3.dist-info/RECORD
